robot_spira_integration.py
spira_robot_framework-1.0.0.dist-info/LICENSE
spira_robot_framework-1.0.0.dist-info/METADATA
spira_robot_framework-1.0.0.dist-info/WHEEL
spira_robot_framework-1.0.0.dist-info/entry_points.txt
spira_robot_framework-1.0.0.dist-info/top_level.txt
spira_robot_framework-1.0.0.dist-info/RECORD
